lpass_auth/__init__.py
lpass_auth/__main__.py
lpass_auth/api.py
lpass_auth/cli.py
lpass_auth-1.0.1.dist-info/entry_points.txt
lpass_auth-1.0.1.dist-info/WHEEL
lpass_auth-1.0.1.dist-info/METADATA
lpass_auth-1.0.1.dist-info/RECORD
