Metadata-Version: 2.1
Name: lpass-auth
Version: 1.0.1
Summary: A command-line client for LastPass Authenticator.
Home-page: https://github.com/SuperSonicHub1/lpass-auth
License: Unlicense
Keywords: lastpass,cli,two-factor
Author: Kyle Anthony Williams
Author-email: kyle.anthony.williams2@gmail.com
Requires-Python: >=3.8,<4.0
Classifier: License :: Other/Proprietary License
Classifier: License :: Public Domain
Classifier: Programming Language :: Python :: 3
Classifier: Programming Language :: Python :: 3.10
Classifier: Programming Language :: Python :: 3.8
Classifier: Programming Language :: Python :: 3.9
Classifier: Topic :: Internet
Classifier: Topic :: Security
Requires-Dist: SecretStorage (>=3.3.1,<4.0.0)
Requires-Dist: keyring (>=23.2.1,<24.0.0)
Requires-Dist: pycryptodome (>=3.11.0,<4.0.0)
Requires-Dist: pyotp (>=2.6.0,<3.0.0)
Requires-Dist: requests (>=2.26.0,<3.0.0)
Project-URL: Documentation, https://github.com/SuperSonicHub1/lpass-auth#readme
Project-URL: Repository, https://github.com/SuperSonicHub1/lpass-auth
